<?xml version="1.0" encoding="utf-8"?>
<!DOCTYPE urlrewrite PUBLIC "-//tuckey.org//DTD UrlRewrite 4.0//EN"
        "http://www.tuckey.org/res/dtds/urlrewrite4.0.dtd">

<!--

    Configuration file for UrlRewriteFilter
    http://www.tuckey.org/urlrewrite/

-->
<urlrewrite>

    <rule>
        <note>
            The rule means that requests to /test/status/ will be redirected to /rewrite-status
            the url will be rewritten.
        </note>
        <from>/test/status/</from>
        <to type="redirect">%{context-path}/rewrite-status</to>
    </rule>


    <outbound-rule>
        <note>
            The outbound-rule specifies that when response.encodeURL is called (if you are using JSTL c:url)
            the url /rewrite-status will be rewritten to /test/status/.

            The above rule and this outbound-rule means that end users should never see the
            url /rewrite-status only /test/status/ both in thier location bar and in hyperlinks
            in your pages.
        </note>
        <from>/rewrite-status</from>
        <to>/test/status/</to>
    </outbound-rule>

        <rule>
                <from>^/$</from>
                <to type="redirect" last="true">/readme</to>
        </rule>

        <rule>
                <from>^/readme$</from>
                <to type="forward">/readme-tnoodle.md</to>
        </rule>
        <rule>
                <from>^/readme.md$</from>
                <to type="forward">/readme-tnoodle.md</to>
        </rule>
        <rule>
                <from>^/readme/scramble$</from>
                <to type="forward">/readme-scramble.md</to>
        </rule>

</urlrewrite>
